{
  "answer": "已阅读 10 个网页\n\n根据近期多家券商的分析和市场动态，受供需关系影响，贵金属（黄金、白银）、工业金属（铜、铝）以及部分战略小金属（钨、稀土等） 已成为市场热点-\n1\n-\n3\n-\n7\n。以下是这些热点金属的具体情况、驱动逻辑以及对应的ETF产品。\n\n近期受供需关系影响的金属热点及驱动逻辑\n\n近期金属市场的热度主要由地缘政治风险、供给端的刚性约束以及新兴需求（如AI和新能源）的增长共同驱动-\n1\n-\n5\n-\n9\n。\n\n金属类别\t具体品种\t核心驱动逻辑\n贵金属\t黄金、白银\t地缘冲突（如美伊局势） 引发避险需求，全球央行持续购金提供长期支撑-\n1\n-\n3\n-\n7\n。\n工业金属\t铜\t供需错配：矿山供给偏紧，同时AI投资、电网建设等新需求旺盛-\n1\n-\n5\n-\n9\n。\n\t铝\t供给威胁：地缘冲突可能影响主要产国（如伊朗）的生产和运输，全球库存较低-\n3\n。\n战略小金属\t钨\t供应刚性缩减：国内指标收紧，叠加现货流通紧张，价格走强-\n1\n-\n7\n-\n10\n。\n\t稀土\t战略价值凸显：节后价格回升，作为关键战略资源受重视-\n1\n-\n9\n。\n对应的ETF产品\n\n你可以通过投资以下ETF来便捷地布局上述金属板块。这些ETF主要分为两类：一类是涵盖多种有色金属的综合性ETF，另一类是聚焦于工业金属的主题性ETF。\n\n基金简称\t基金代码\t跟踪指数\t主要覆盖的金属热点\n国泰中证有色金属ETF\t159881\t中证有色金属指数\t综合性较强，涵盖黄金、铜、铝、稀土、钨等-\n2\n-\n4\n。\n有色金属ETF天弘\t159157\t中证工业有色金属主题指数\t聚焦工业金属，涵盖铜、铝、锡等，近期持续获得资金净流入-\n8\n-\n10\n。\n有色金属ETF基金\t516650\t中证细分有色金属产业主题指数\t聚焦黄金、铜铝等工业金属及小金属-\n2\n。\n工业有色ETF博时\t具体代码需查询公告\t中证工业有色金属主题指数\t新上市基金，聚焦工业有色金属主题-\n6\n。\n\n需要注意的是，投资ETF前应仔细阅读其招募说明书，了解其具体的持仓和风险特征。金属价格波动较大，且受全球宏观经济、货币政策等多重因素影响，投资需谨慎-\n1\n-\n7\n。\n\n你是更看好铜、铝这类工业金属的顺周期机会，还是想配置一些黄金来对冲风险？告诉我你的偏好，我可以帮你筛选表现更契合的ETF。\n\n10 个网页\n",
  "references": [
    {
      "title": "m.163.com",
      "url": "https://m.163.com/dy/article/KN1IHAO805568W0A.html"
    },
    {
      "title": "vip.stock.finance.sina.com.cn",
      "url": "http://vip.stock.finance.sina.com.cn/q/go.php/vReport_Show/kind/lastest/rptid/825702180275/index.phtml"
    },
    {
      "title": "stock.finance.sina.com.cn",
      "url": "http://stock.finance.sina.com.cn/stock/go.php/vReport_Show/kind/industry/rptid/825685980364/index.phtml"
    },
    {
      "title": "news.mysteel.com",
      "url": "https://news.mysteel.com/a/26030210/AC7B8AB3AD27F934.html"
    },
    {
      "title": "stockfinance.sina.cn",
      "url": "http://stockfinance.sina.cn/stock/go.php/paper/reportid/825773012226/index.phtml?vt=4"
    },
    {
      "title": "toutiao.com",
      "url": "https://www.toutiao.com/article/7612474692271620648/"
    },
    {
      "title": "4g.stockstar.com",
      "url": "https://4g.stockstar.com/detail/SS2026030300013160"
    },
    {
      "title": "stock.finance.sina.com.cn",
      "url": "https://stock.finance.sina.com.cn/fundInfo/view/FundInfo_LSJZ.php?symbol=159881"
    },
    {
      "title": "sfccn.com",
      "url": "https://www.sfccn.com/2026/3-3/zNMDE1MjBfMjExMTgzNg.html"
    },
    {
      "title": "fund.stockstar.com",
      "url": "http://fund.stockstar.com/SN2026030100008321.shtml"
    }
  ]
}